django_config_gen/models.py
django_config_gen/__init__.py
django_config_gen/management/__init__.py
django_config_gen/management/defaults.py
django_config_gen/management/commands/print_settings.py
django_config_gen/management/commands/config_gen.py
django_config_gen/management/commands/__init__.py
django_config_gen/management/commands/example_templates/apache_via_nginx_ports
django_config_gen/management/commands/example_templates/basic_apache
django_config_gen/management/commands/example_templates/nginx
django_config_gen/management/commands/example_templates/django.wsgi
django_config_gen/management/commands/example_templates/apache_via_nginx
django_config_gen/tests/test.py
django_config_gen/tests/__init__.py
django_config_gen-1.1.0.dist-info/DESCRIPTION.rst
django_config_gen-1.1.0.dist-info/RECORD
django_config_gen-1.1.0.dist-info/metadata.json
django_config_gen-1.1.0.dist-info/WHEEL
django_config_gen-1.1.0.dist-info/pbr.json
django_config_gen-1.1.0.dist-info/METADATA
django_config_gen-1.1.0.dist-info/top_level.txt
